{
  "kind": "collectionType",
  "collectionName": "used_softwares",
  "info": {
    "singularName": "used-software",
    "pluralName": "used-softwares",
    "displayName": "UsedSoftware",
    "description": ""
  },
  "options": {
    "draftAndPublish": true
  },
  "pluginOptions": {},
  "attributes": {
    "influenced": {
      "type": "boolean",
      "default": false,
      "required": true
    },
    "periods": {
      "type": "relation",
      "relation": "oneToMany",
      "target": "api::used-software-period.used-software-period",
      "mappedBy": "software"
    }
  }
}
